query_tables/__init__.py
query_tables/exceptions.py
query_tables/query_table.py
query_tables/tables.py
query_tables/translate.py
query_tables/utils.py
query_tables/cache/__init__.py
query_tables/cache/async_cache_query.py
query_tables/cache/async_redis_cache.py
query_tables/cache/base_cache.py
query_tables/cache/cache_query.py
query_tables/cache/redis_cache.py
query_tables/db/__init__.py
query_tables/db/base_db_query.py
query_tables/db/db_postgres.py
query_tables/db/db_sqlite.py
query_tables/locale/en/LC_MESSAGES/query_tables.mo
query_tables/locale/en/LC_MESSAGES/query_tables.po
query_tables/query/__init__.py
query_tables/query/base_query.py
query_tables/query/condition.py
query_tables/query/functions.py
query_tables/query/join_table.py
query_tables/query/query.py
query_tables-1.16.28.dist-info/licenses/LICENSE
query_tables-1.16.28.dist-info/METADATA
query_tables-1.16.28.dist-info/WHEEL
query_tables-1.16.28.dist-info/top_level.txt
query_tables-1.16.28.dist-info/RECORD
