Metadata-Version: 2.4
Name: query_tables
Version: 1.16.28
Summary: Запросы в объектном стиле без моделей с поддержкой кеша данных (CORMless)
Author: Антон Глызин
Author-email: tosha.glyzin@mail.ru
License: MIT
Project-URL: Releases, https://github.com/AntonGlyzin/query_tables/releases
Project-URL: Github, https://github.com/AntonGlyzin/query_tables
Project-URL: Read the docs, https://query-tables.readthedocs.io
Keywords: cache aiocache orm sql table redis postgres sqlite asyncio python
Classifier: Intended Audience :: Developers
Classifier: Programming Language :: Python :: 3.9
Classifier: Programming Language :: Python :: 3.10
Classifier: Programming Language :: Python :: 3.11
Classifier: Programming Language :: Python :: 3.12
Classifier: Programming Language :: Python :: 3.13
Classifier: Topic :: Software Development :: Libraries
Requires-Python: >=3.9
License-File: LICENSE
Requires-Dist: cachetools<=6.0.0
Requires-Dist: aiosqlite<=0.21.0
Requires-Dist: psycopg2<=2.9.10
Requires-Dist: asyncpg<=0.30.0
Requires-Dist: redis<=6.2.0
Requires-Dist: aiocache<=0.12.3
Dynamic: author
Dynamic: author-email
Dynamic: classifier
Dynamic: description
Dynamic: description-content-type
Dynamic: keywords
Dynamic: license
Dynamic: license-file
Dynamic: project-url
Dynamic: requires-dist
Dynamic: requires-python
Dynamic: summary
